{
  "Scripts": [
    {
      "ConnectionId": "719772f8-053d-48f7-9760-3ac83132700f",
      "Schema": "common",
      "TableName": "VRDevProject",
      "Note": null,
      "Settings": {
        "$type": "Vanrise.DevTools.Business.MergeGeneratedScriptItem, Vanrise.DevTools.Business",
        "DataRows": [
          {
            "FieldValues": {
              "ID": "c3cbcab4-fc87-4528-9323-decb35cec62d",
              "Name": "VR_NumberPrefix",
              "AssemblyID": null,
              "CreatedTime": "2019-09-12T16:17:18.447",
              "LastModifiedTime": "2019-09-12T16:17:18.447"
            }
          }
        ],
        "Columns": [
          {
            "$type": "Vanrise.DevTools.Business.MergeGeneratedScriptItemColumn, Vanrise.DevTools.Business",
            "ColumnName": "ID",
            "IsIdentifier": true,
            "IncludeInInsert": true,
            "IncludeInUpdate": true
          },
          {
            "$type": "Vanrise.DevTools.Business.MergeGeneratedScriptItemColumn, Vanrise.DevTools.Business",
            "ColumnName": "Name",
            "IsIdentifier": false,
            "IncludeInInsert": true,
            "IncludeInUpdate": true
          },
          {
            "$type": "Vanrise.DevTools.Business.MergeGeneratedScriptItemColumn, Vanrise.DevTools.Business",
            "ColumnName": "AssemblyID",
            "IsIdentifier": false,
            "IncludeInInsert": true,
            "IncludeInUpdate": true
          },
          {
            "$type": "Vanrise.DevTools.Business.MergeGeneratedScriptItemColumn, Vanrise.DevTools.Business",
            "ColumnName": "CreatedTime",
            "IsIdentifier": false,
            "IncludeInInsert": true,
            "IncludeInUpdate": true
          },
          {
            "$type": "Vanrise.DevTools.Business.MergeGeneratedScriptItemColumn, Vanrise.DevTools.Business",
            "ColumnName": "LastModifiedTime",
            "IsIdentifier": false,
            "IncludeInInsert": true,
            "IncludeInUpdate": true
          }
        ],
        "IsIdentity": false,
        "Variables": [],
        "LastWhereCondition": "ID = 'c3cbcab4-fc87-4528-9323-decb35cec62d'",
        "LastJoinStatement": null,
        "ConfigId": "9837cad1-1f8f-4edf-8aab-25864c4ef842"
      },
      "Title": "Merge"
    },
    {
      "$type": "Vanrise.DevTools.Entities.GeneratedScriptItemTable, Vanrise.DevTools.Entities",
      "ConnectionId": "719772f8-053d-48f7-9760-3ac83132700f",
      "Schema": "genericdata",
      "TableName": "DataRecordType",
      "Note": null,
      "Settings": {
        "$type": "Vanrise.DevTools.Business.MergeGeneratedScriptItem, Vanrise.DevTools.Business",
        "ConfigId": "9837cad1-1f8f-4edf-8aab-25864c4ef842",
        "Columns": [
          {
            "$type": "Vanrise.DevTools.Business.MergeGeneratedScriptItemColumn, Vanrise.DevTools.Business",
            "ColumnName": "ID",
            "IsIdentifier": true,
            "IncludeInInsert": true,
            "IncludeInUpdate": true
          },
          {
            "$type": "Vanrise.DevTools.Business.MergeGeneratedScriptItemColumn, Vanrise.DevTools.Business",
            "ColumnName": "DevProjectID",
            "IsIdentifier": false,
            "IncludeInInsert": true,
            "IncludeInUpdate": true
          },
          {
            "$type": "Vanrise.DevTools.Business.MergeGeneratedScriptItemColumn, Vanrise.DevTools.Business",
            "ColumnName": "Name",
            "IsIdentifier": false,
            "IncludeInInsert": true,
            "IncludeInUpdate": true
          },
          {
            "$type": "Vanrise.DevTools.Business.MergeGeneratedScriptItemColumn, Vanrise.DevTools.Business",
            "ColumnName": "ParentID",
            "IsIdentifier": false,
            "IncludeInInsert": true,
            "IncludeInUpdate": true
          },
          {
            "$type": "Vanrise.DevTools.Business.MergeGeneratedScriptItemColumn, Vanrise.DevTools.Business",
            "ColumnName": "Fields",
            "IsIdentifier": false,
            "IncludeInInsert": true,
            "IncludeInUpdate": true
          },
          {
            "$type": "Vanrise.DevTools.Business.MergeGeneratedScriptItemColumn, Vanrise.DevTools.Business",
            "ColumnName": "ExtraFieldsEvaluator",
            "IsIdentifier": false,
            "IncludeInInsert": true,
            "IncludeInUpdate": true
          },
          {
            "$type": "Vanrise.DevTools.Business.MergeGeneratedScriptItemColumn, Vanrise.DevTools.Business",
            "ColumnName": "Settings",
            "IsIdentifier": false,
            "IncludeInInsert": true,
            "IncludeInUpdate": true
          },
          {
            "$type": "Vanrise.DevTools.Business.MergeGeneratedScriptItemColumn, Vanrise.DevTools.Business",
            "ColumnName": "CreatedTime",
            "IsIdentifier": false,
            "IncludeInInsert": true,
            "IncludeInUpdate": true
          },
          {
            "$type": "Vanrise.DevTools.Business.MergeGeneratedScriptItemColumn, Vanrise.DevTools.Business",
            "ColumnName": "LastModifiedTime",
            "IsIdentifier": false,
            "IncludeInInsert": true,
            "IncludeInUpdate": true
          }
        ],
        "DataRows": [
          {
            "$type": "Vanrise.DevTools.Entities.GeneratedScriptItemTableRow, Vanrise.DevTools.Entities",
            "FieldValues": {
              "ID": "630e82e3-e187-4738-a40d-387f07cb4759",
              "DevProjectID": "c3cbcab4-fc87-4528-9323-decb35cec62d",
              "Name": "VRNumberPrefix",
              "ParentID": null,
              "Fields": "{\"$type\":\"System.Collections.Generic.List`1[[Vanrise.GenericData.Entities.DataRecordField, Vanrise.GenericData.Entities]], mscorlib\",\"$values\":[{\"$type\":\"Vanrise.GenericData.Entities.DataRecordField, Vanrise.GenericData.Entities\",\"Name\":\"Id\",\"Title\":\"Id\",\"Type\":{\"$type\":\"Vanrise.GenericData.MainExtensions.DataRecordFields.FieldNumberType, Vanrise.GenericData.MainExtensions\",\"ConfigId\":\"75aef329-27bd-4108-b617-f5cc05ff2aa3\",\"ViewerEditor\":\"vr-genericdata-fieldtype-number-viewereditor\",\"RuntimeEditor\":\"vr-genericdata-fieldtype-number-runtimeeditor\",\"DataPrecision\":0,\"DataType\":1,\"IsNullable\":false,\"CanRoundValue\":true,\"DetailViewerEditor\":\"vr-genericdata-datarecordfield-defaultdetailviewer\",\"ShowDefaultValue\":true,\"OrderType\":0,\"StoreValueSerialized\":false},\"IsInheritedFromExtraField\":false},{\"$type\":\"Vanrise.GenericData.Entities.DataRecordField, Vanrise.GenericData.Entities\",\"Name\":\"Number\",\"Title\":\"Number\",\"Type\":{\"$type\":\"Vanrise.GenericData.MainExtensions.DataRecordFields.FieldTextType, Vanrise.GenericData.MainExtensions\",\"ConfigId\":\"3f29315e-b542-43b8-9618-7de216cd9653\",\"RuntimeEditor\":\"vr-genericdata-fieldtype-text-runtimeeditor\",\"ViewerEditor\":\"vr-genericdata-fieldtype-text-viewereditor\",\"OrderType\":1,\"DetailViewerEditor\":\"vr-genericdata-datarecordfield-defaultdetailviewer\",\"ShowDefaultValue\":true,\"StoreValueSerialized\":false,\"CanRoundValue\":false},\"IsInheritedFromExtraField\":false},{\"$type\":\"Vanrise.GenericData.Entities.DataRecordField, Vanrise.GenericData.Entities\",\"Name\":\"Type\",\"Title\":\"Type\",\"Type\":{\"$type\":\"Vanrise.GenericData.MainExtensions.DataRecordFields.FieldBusinessEntityType, Vanrise.GenericData.MainExtensions\",\"ConfigId\":\"2e16c3d4-837b-4433-b80e-7c02f6d71467\",\"RuntimeEditor\":\"vr-genericdata-fieldtype-businessentity-runtimeeditor\",\"ViewerEditor\":\"vr-genericdata-fieldtype-businessentity-viewereditor\",\"OrderType\":1,\"BusinessEntityDefinitionId\":\"fe36264a-1db1-4c1d-9228-036a43195d4d\",\"IsNullable\":false,\"DependantFields\":{\"$type\":\"System.Collections.Generic.List`1[[Vanrise.GenericData.MainExtensions.DataRecordFields.FieldBusinessEntityTypeDependantField, Vanrise.GenericData.MainExtensions]], mscorlib\",\"$values\":[]},\"DetailViewerEditor\":\"vr-genericdata-datarecordfield-defaultdetailviewer\",\"ShowDefaultValue\":true,\"StoreValueSerialized\":false,\"CanRoundValue\":false},\"IsInheritedFromExtraField\":false},{\"$type\":\"Vanrise.GenericData.Entities.DataRecordField, Vanrise.GenericData.Entities\",\"Name\":\"IsExact\",\"Title\":\"Exact\",\"Type\":{\"$type\":\"Vanrise.GenericData.MainExtensions.DataRecordFields.FieldBooleanType, Vanrise.GenericData.MainExtensions\",\"ConfigId\":\"a77fad19-d044-40d8-9d04-6362b79b177b\",\"RuntimeEditor\":\"vr-genericdata-fieldtype-boolean-runtimeeditor\",\"IsNullable\":false,\"ViewerEditor\":\"vr-genericdata-fieldtype-boolean-viewereditor\",\"DetailViewerEditor\":\"vr-genericdata-datarecordfield-defaultdetailviewer\",\"ShowDefaultValue\":true,\"OrderType\":0,\"StoreValueSerialized\":false,\"CanRoundValue\":false},\"IsInheritedFromExtraField\":false},{\"$type\":\"Vanrise.GenericData.Entities.DataRecordField, Vanrise.GenericData.Entities\",\"Name\":\"CreatedBy\",\"Title\":\"Created By\",\"Type\":{\"$type\":\"Vanrise.GenericData.MainExtensions.DataRecordFields.FieldBusinessEntityType, Vanrise.GenericData.MainExtensions\",\"ConfigId\":\"2e16c3d4-837b-4433-b80e-7c02f6d71467\",\"RuntimeEditor\":\"vr-genericdata-fieldtype-businessentity-runtimeeditor\",\"ViewerEditor\":\"vr-genericdata-fieldtype-businessentity-viewereditor\",\"OrderType\":1,\"BusinessEntityDefinitionId\":\"217a8f71-1dd6-4613-8ae2-540a510f5ff5\",\"IsNullable\":false,\"DependantFields\":{\"$type\":\"System.Collections.Generic.List`1[[Vanrise.GenericData.MainExtensions.DataRecordFields.FieldBusinessEntityTypeDependantField, Vanrise.GenericData.MainExtensions]], mscorlib\",\"$values\":[]},\"DetailViewerEditor\":\"vr-genericdata-datarecordfield-defaultdetailviewer\",\"ShowDefaultValue\":true,\"StoreValueSerialized\":false,\"CanRoundValue\":false},\"IsInheritedFromExtraField\":false},{\"$type\":\"Vanrise.GenericData.Entities.DataRecordField, Vanrise.GenericData.Entities\",\"Name\":\"CreatedTime\",\"Title\":\"Created Time\",\"Type\":{\"$type\":\"Vanrise.GenericData.MainExtensions.DataRecordFields.FieldDateTimeType, Vanrise.GenericData.MainExtensions\",\"ConfigId\":\"b8712417-83ab-4d4b-9ee1-109d20ceb909\",\"RuntimeEditor\":\"vr-genericdata-fieldtype-datetime-runtimeeditor\",\"ViewerEditor\":\"vr-genericdata-fieldtype-datetime-viewereditor\",\"RuntimeViewSettingEditor\":\"vr-genericdata-fieldtype-datetime-settings\",\"ShowDefaultValue\":false,\"DataType\":0,\"IsNullable\":false,\"DetailViewerEditor\":\"vr-genericdata-datarecordfield-defaultdetailviewer\",\"OrderType\":0,\"StoreValueSerialized\":false,\"CanRoundValue\":false},\"IsInheritedFromExtraField\":false},{\"$type\":\"Vanrise.GenericData.Entities.DataRecordField, Vanrise.GenericData.Entities\",\"Name\":\"LastModifiedBy\",\"Title\":\"Last Modified By\",\"Type\":{\"$type\":\"Vanrise.GenericData.MainExtensions.DataRecordFields.FieldBusinessEntityType, Vanrise.GenericData.MainExtensions\",\"ConfigId\":\"2e16c3d4-837b-4433-b80e-7c02f6d71467\",\"RuntimeEditor\":\"vr-genericdata-fieldtype-businessentity-runtimeeditor\",\"ViewerEditor\":\"vr-genericdata-fieldtype-businessentity-viewereditor\",\"OrderType\":1,\"BusinessEntityDefinitionId\":\"217a8f71-1dd6-4613-8ae2-540a510f5ff5\",\"IsNullable\":false,\"DependantFields\":{\"$type\":\"System.Collections.Generic.List`1[[Vanrise.GenericData.MainExtensions.DataRecordFields.FieldBusinessEntityTypeDependantField, Vanrise.GenericData.MainExtensions]], mscorlib\",\"$values\":[]},\"DetailViewerEditor\":\"vr-genericdata-datarecordfield-defaultdetailviewer\",\"ShowDefaultValue\":true,\"StoreValueSerialized\":false,\"CanRoundValue\":false},\"IsInheritedFromExtraField\":false},{\"$type\":\"Vanrise.GenericData.Entities.DataRecordField, Vanrise.GenericData.Entities\",\"Name\":\"LastModifiedTime\",\"Title\":\"Last Modified Time\",\"Type\":{\"$type\":\"Vanrise.GenericData.MainExtensions.DataRecordFields.FieldDateTimeType, Vanrise.GenericData.MainExtensions\",\"ConfigId\":\"b8712417-83ab-4d4b-9ee1-109d20ceb909\",\"RuntimeEditor\":\"vr-genericdata-fieldtype-datetime-runtimeeditor\",\"ViewerEditor\":\"vr-genericdata-fieldtype-datetime-viewereditor\",\"RuntimeViewSettingEditor\":\"vr-genericdata-fieldtype-datetime-settings\",\"ShowDefaultValue\":false,\"DataType\":0,\"IsNullable\":false,\"DetailViewerEditor\":\"vr-genericdata-datarecordfield-defaultdetailviewer\",\"OrderType\":0,\"StoreValueSerialized\":false,\"CanRoundValue\":false},\"IsInheritedFromExtraField\":false}]}",
              "ExtraFieldsEvaluator": null,
              "Settings": "{\"$type\":\"Vanrise.GenericData.Entities.DataRecordTypeSettings, Vanrise.GenericData.Entities\",\"DateTimeField\":\"CreatedTime\",\"IdField\":\"Id\"}",
              "CreatedTime": "2019-07-01T14:44:45.813",
              "LastModifiedTime": "2019-09-25T14:15:17.487"
            }
          },
          {
            "$type": "Vanrise.DevTools.Entities.GeneratedScriptItemTableRow, Vanrise.DevTools.Entities",
            "FieldValues": {
              "ID": "79f76dca-ec83-4919-a09e-6f142578e7f7",
              "DevProjectID": "c3cbcab4-fc87-4528-9323-decb35cec62d",
              "Name": "VRNumberPrefixType",
              "ParentID": null,
              "Fields": "{\"$type\":\"System.Collections.Generic.List`1[[Vanrise.GenericData.Entities.DataRecordField, Vanrise.GenericData.Entities]], mscorlib\",\"$values\":[{\"$type\":\"Vanrise.GenericData.Entities.DataRecordField, Vanrise.GenericData.Entities\",\"Name\":\"Id\",\"Title\":\"Id\",\"Type\":{\"$type\":\"Vanrise.GenericData.MainExtensions.DataRecordFields.FieldGuidType, Vanrise.GenericData.MainExtensions\",\"ConfigId\":\"ebd22f77-6275-4194-8710-7bf3063dcb68\",\"RuntimeEditor\":\"vr-genericdata-fieldtype-guid-runtimeeditor\",\"OrderType\":1,\"ViewerEditor\":\"vr-genericdata-fieldtype-guid-viewereditor\",\"IsNullable\":false,\"DetailViewerEditor\":\"vr-genericdata-datarecordfield-defaultdetailviewer\",\"ShowDefaultValue\":true,\"StoreValueSerialized\":false,\"CanRoundValue\":false},\"IsInheritedFromExtraField\":false},{\"$type\":\"Vanrise.GenericData.Entities.DataRecordField, Vanrise.GenericData.Entities\",\"Name\":\"Name\",\"Title\":\"Name\",\"Type\":{\"$type\":\"Vanrise.GenericData.MainExtensions.DataRecordFields.FieldTextType, Vanrise.GenericData.MainExtensions\",\"ConfigId\":\"3f29315e-b542-43b8-9618-7de216cd9653\",\"RuntimeEditor\":\"vr-genericdata-fieldtype-text-runtimeeditor\",\"ViewerEditor\":\"vr-genericdata-fieldtype-text-viewereditor\",\"OrderType\":1,\"DetailViewerEditor\":\"vr-genericdata-datarecordfield-defaultdetailviewer\",\"ShowDefaultValue\":true,\"StoreValueSerialized\":false,\"CanRoundValue\":false},\"IsInheritedFromExtraField\":false},{\"$type\":\"Vanrise.GenericData.Entities.DataRecordField, Vanrise.GenericData.Entities\",\"Name\":\"CreatedBy\",\"Title\":\"Created By\",\"Type\":{\"$type\":\"Vanrise.GenericData.MainExtensions.DataRecordFields.FieldBusinessEntityType, Vanrise.GenericData.MainExtensions\",\"ConfigId\":\"2e16c3d4-837b-4433-b80e-7c02f6d71467\",\"RuntimeEditor\":\"vr-genericdata-fieldtype-businessentity-runtimeeditor\",\"ViewerEditor\":\"vr-genericdata-fieldtype-businessentity-viewereditor\",\"OrderType\":1,\"BusinessEntityDefinitionId\":\"217a8f71-1dd6-4613-8ae2-540a510f5ff5\",\"IsNullable\":false,\"DependantFields\":{\"$type\":\"System.Collections.Generic.List`1[[Vanrise.GenericData.MainExtensions.DataRecordFields.FieldBusinessEntityTypeDependantField, Vanrise.GenericData.MainExtensions]], mscorlib\",\"$values\":[]},\"DetailViewerEditor\":\"vr-genericdata-datarecordfield-defaultdetailviewer\",\"ShowDefaultValue\":true,\"StoreValueSerialized\":false,\"CanRoundValue\":false},\"IsInheritedFromExtraField\":false},{\"$type\":\"Vanrise.GenericData.Entities.DataRecordField, Vanrise.GenericData.Entities\",\"Name\":\"CreatedTime\",\"Title\":\"Created Time\",\"Type\":{\"$type\":\"Vanrise.GenericData.MainExtensions.DataRecordFields.FieldDateTimeType, Vanrise.GenericData.MainExtensions\",\"ConfigId\":\"b8712417-83ab-4d4b-9ee1-109d20ceb909\",\"RuntimeEditor\":\"vr-genericdata-fieldtype-datetime-runtimeeditor\",\"ViewerEditor\":\"vr-genericdata-fieldtype-datetime-viewereditor\",\"RuntimeViewSettingEditor\":\"vr-genericdata-fieldtype-datetime-settings\",\"ShowDefaultValue\":false,\"DataType\":0,\"IsNullable\":false,\"DetailViewerEditor\":\"vr-genericdata-datarecordfield-defaultdetailviewer\",\"OrderType\":0,\"StoreValueSerialized\":false,\"CanRoundValue\":false},\"IsInheritedFromExtraField\":false},{\"$type\":\"Vanrise.GenericData.Entities.DataRecordField, Vanrise.GenericData.Entities\",\"Name\":\"LastModifiedBy\",\"Title\":\"Last Modified By\",\"Type\":{\"$type\":\"Vanrise.GenericData.MainExtensions.DataRecordFields.FieldBusinessEntityType, Vanrise.GenericData.MainExtensions\",\"ConfigId\":\"2e16c3d4-837b-4433-b80e-7c02f6d71467\",\"RuntimeEditor\":\"vr-genericdata-fieldtype-businessentity-runtimeeditor\",\"ViewerEditor\":\"vr-genericdata-fieldtype-businessentity-viewereditor\",\"OrderType\":1,\"BusinessEntityDefinitionId\":\"217a8f71-1dd6-4613-8ae2-540a510f5ff5\",\"IsNullable\":false,\"DependantFields\":{\"$type\":\"System.Collections.Generic.List`1[[Vanrise.GenericData.MainExtensions.DataRecordFields.FieldBusinessEntityTypeDependantField, Vanrise.GenericData.MainExtensions]], mscorlib\",\"$values\":[]},\"DetailViewerEditor\":\"vr-genericdata-datarecordfield-defaultdetailviewer\",\"ShowDefaultValue\":true,\"StoreValueSerialized\":false,\"CanRoundValue\":false},\"IsInheritedFromExtraField\":false},{\"$type\":\"Vanrise.GenericData.Entities.DataRecordField, Vanrise.GenericData.Entities\",\"Name\":\"LastModifiedTime\",\"Title\":\"Last Modified Time\",\"Type\":{\"$type\":\"Vanrise.GenericData.MainExtensions.DataRecordFields.FieldDateTimeType, Vanrise.GenericData.MainExtensions\",\"ConfigId\":\"b8712417-83ab-4d4b-9ee1-109d20ceb909\",\"RuntimeEditor\":\"vr-genericdata-fieldtype-datetime-runtimeeditor\",\"ViewerEditor\":\"vr-genericdata-fieldtype-datetime-viewereditor\",\"RuntimeViewSettingEditor\":\"vr-genericdata-fieldtype-datetime-settings\",\"ShowDefaultValue\":false,\"DataType\":0,\"IsNullable\":false,\"DetailViewerEditor\":\"vr-genericdata-datarecordfield-defaultdetailviewer\",\"OrderType\":0,\"StoreValueSerialized\":false,\"CanRoundValue\":false},\"IsInheritedFromExtraField\":false}]}",
              "ExtraFieldsEvaluator": null,
              "Settings": "{\"$type\":\"Vanrise.GenericData.Entities.DataRecordTypeSettings, Vanrise.GenericData.Entities\",\"DateTimeField\":\"CreatedTime\",\"IdField\":\"Id\"}",
              "CreatedTime": "2019-07-01T14:44:45.813",
              "LastModifiedTime": "2019-10-24T14:01:07.15"
            }
          }
        ],
        "Variables": null,
        "LastWhereCondition": "DevProjectID = 'c3cbcab4-fc87-4528-9323-decb35cec62d'",
        "LastJoinStatement": null,
        "IsIdentity": false
      },
      "Title": "Merge"
    },
    {
      "ConnectionId": "719772f8-053d-48f7-9760-3ac83132700f",
      "Schema": "genericdata",
      "TableName": "DataRecordStorage",
      "Note": null,
      "Settings": {
        "$type": "Vanrise.DevTools.Business.MergeGeneratedScriptItem, Vanrise.DevTools.Business",
        "DataRows": [
          {
            "FieldValues": {
              "ID": "a70a6875-0820-42c2-9ec0-0591ba6f2778",
              "Name": "VRNumberPrefix",
              "DataRecordTypeID": "630e82e3-e187-4738-a40d-387f07cb4759",
              "DataStoreID": "608a5cc4-a933-4bf3-83a7-3797edd0bb41",
              "Settings": "{\"$type\":\"Vanrise.GenericData.SQLDataStorage.SQLDataRecordStorageSettings, Vanrise.GenericData.SQLDataStorage\",\"TableName\":\"VRNumberPrefix\",\"TableSchema\":\"genericdata\",\"Columns\":{\"$type\":\"System.Collections.Generic.List`1[[Vanrise.GenericData.SQLDataStorage.SQLDataRecordStorageColumn, Vanrise.GenericData.SQLDataStorage]], mscorlib\",\"$values\":[{\"$type\":\"Vanrise.GenericData.SQLDataStorage.SQLDataRecordStorageColumn, Vanrise.GenericData.SQLDataStorage\",\"ColumnName\":\"Id\",\"SQLDataType\":\"int\",\"ValueExpression\":\"Id\",\"IsUnique\":false,\"IsIdentity\":true},{\"$type\":\"Vanrise.GenericData.SQLDataStorage.SQLDataRecordStorageColumn, Vanrise.GenericData.SQLDataStorage\",\"ColumnName\":\"Number\",\"SQLDataType\":\"varchar(20)\",\"ValueExpression\":\"Number\",\"IsUnique\":true,\"IsIdentity\":false},{\"$type\":\"Vanrise.GenericData.SQLDataStorage.SQLDataRecordStorageColumn, Vanrise.GenericData.SQLDataStorage\",\"ColumnName\":\"Type\",\"SQLDataType\":\"uniqueidentifier\",\"ValueExpression\":\"Type\",\"IsUnique\":false,\"IsIdentity\":false},{\"$type\":\"Vanrise.GenericData.SQLDataStorage.SQLDataRecordStorageColumn, Vanrise.GenericData.SQLDataStorage\",\"ColumnName\":\"IsExact\",\"SQLDataType\":\"bit\",\"ValueExpression\":\"IsExact\",\"IsUnique\":false,\"IsIdentity\":false},{\"$type\":\"Vanrise.GenericData.SQLDataStorage.SQLDataRecordStorageColumn, Vanrise.GenericData.SQLDataStorage\",\"ColumnName\":\"CreatedBy\",\"SQLDataType\":\"int\",\"ValueExpression\":\"CreatedBy\",\"IsUnique\":false,\"IsIdentity\":false},{\"$type\":\"Vanrise.GenericData.SQLDataStorage.SQLDataRecordStorageColumn, Vanrise.GenericData.SQLDataStorage\",\"ColumnName\":\"CreatedTime\",\"SQLDataType\":\"datetime\",\"ValueExpression\":\"CreatedTime\",\"IsUnique\":false,\"IsIdentity\":false},{\"$type\":\"Vanrise.GenericData.SQLDataStorage.SQLDataRecordStorageColumn, Vanrise.GenericData.SQLDataStorage\",\"ColumnName\":\"LastModifiedBy\",\"SQLDataType\":\"int\",\"ValueExpression\":\"LastModifiedBy\",\"IsUnique\":false,\"IsIdentity\":false},{\"$type\":\"Vanrise.GenericData.SQLDataStorage.SQLDataRecordStorageColumn, Vanrise.GenericData.SQLDataStorage\",\"ColumnName\":\"LastModifiedTime\",\"SQLDataType\":\"datetime\",\"ValueExpression\":\"LastModifiedTime\",\"IsUnique\":false,\"IsIdentity\":false}]},\"NullableFields\":{\"$type\":\"System.Collections.Generic.List`1[[Vanrise.GenericData.SQLDataStorage.NullableField, Vanrise.GenericData.SQLDataStorage]], mscorlib\",\"$values\":[]},\"IncludeQueueItemId\":false,\"GenerateRecordIds\":false,\"DateTimeField\":\"CreatedTime\",\"LastModifiedByField\":\"LastModifiedBy\",\"CreatedByField\":\"CreatedBy\",\"LastModifiedTimeField\":\"LastModifiedTime\",\"CreatedTimeField\":\"CreatedTime\",\"EnableUseCaching\":true,\"RequiredLimitResult\":false,\"DontReflectToDB\":false,\"DenyAPICall\":true,\"PermanentFilter\":{\"$type\":\"Vanrise.GenericData.Entities.DataRecordStoragePermanentFilter, Vanrise.GenericData.Entities\"},\"RequiredPermission\":{\"$type\":\"Vanrise.Security.Entities.RequiredPermissionSettings, Vanrise.Security.Entities\",\"Entries\":{\"$type\":\"System.Collections.Generic.List`1[[Vanrise.Security.Entities.RequiredPermissionEntry, Vanrise.Security.Entities]], mscorlib\",\"$values\":[]}},\"FieldsPermissions\":{\"$type\":\"System.Collections.Generic.List`1[[Vanrise.GenericData.Entities.DataRecordStorageFieldsPermission, Vanrise.GenericData.Entities]], mscorlib\",\"$values\":[]}}",
              "State": null,
              "CreatedTime": "2019-07-01T14:44:45.82",
              "LastModifiedTime": "2019-09-25T14:17:45.323"
            }
          },
          {
            "FieldValues": {
              "ID": "36b1b656-a438-4e67-887b-5082126606d2",
              "Name": "VRNumberPrefixType",
              "DataRecordTypeID": "79f76dca-ec83-4919-a09e-6f142578e7f7",
              "DataStoreID": "608a5cc4-a933-4bf3-83a7-3797edd0bb41",
              "Settings": "{\"$type\":\"Vanrise.GenericData.SQLDataStorage.SQLDataRecordStorageSettings, Vanrise.GenericData.SQLDataStorage\",\"TableName\":\"VRNumberPrefixType\",\"TableSchema\":\"genericdata\",\"Columns\":{\"$type\":\"System.Collections.Generic.List`1[[Vanrise.GenericData.SQLDataStorage.SQLDataRecordStorageColumn, Vanrise.GenericData.SQLDataStorage]], mscorlib\",\"$values\":[{\"$type\":\"Vanrise.GenericData.SQLDataStorage.SQLDataRecordStorageColumn, Vanrise.GenericData.SQLDataStorage\",\"ColumnName\":\"Id\",\"SQLDataType\":\"uniqueidentifier\",\"ValueExpression\":\"Id\",\"IsUnique\":false,\"IsIdentity\":false},{\"$type\":\"Vanrise.GenericData.SQLDataStorage.SQLDataRecordStorageColumn, Vanrise.GenericData.SQLDataStorage\",\"ColumnName\":\"DevProjectID\",\"SQLDataType\":\"uniqueidentifier\",\"ValueExpression\":\"DevProjectID\",\"IsUnique\":false,\"IsIdentity\":false},{\"$type\":\"Vanrise.GenericData.SQLDataStorage.SQLDataRecordStorageColumn, Vanrise.GenericData.SQLDataStorage\",\"ColumnName\":\"Name\",\"SQLDataType\":\"varchar(255)\",\"ValueExpression\":\"Name\",\"IsUnique\":true,\"IsIdentity\":false},{\"$type\":\"Vanrise.GenericData.SQLDataStorage.SQLDataRecordStorageColumn, Vanrise.GenericData.SQLDataStorage\",\"ColumnName\":\"CreatedBy\",\"SQLDataType\":\"int\",\"ValueExpression\":\"CreatedBy\",\"IsUnique\":false,\"IsIdentity\":false},{\"$type\":\"Vanrise.GenericData.SQLDataStorage.SQLDataRecordStorageColumn, Vanrise.GenericData.SQLDataStorage\",\"ColumnName\":\"CreatedTime\",\"SQLDataType\":\"datetime\",\"ValueExpression\":\"CreatedTime\",\"IsUnique\":false,\"IsIdentity\":false},{\"$type\":\"Vanrise.GenericData.SQLDataStorage.SQLDataRecordStorageColumn, Vanrise.GenericData.SQLDataStorage\",\"ColumnName\":\"LastModifiedBy\",\"SQLDataType\":\"int\",\"ValueExpression\":\"LastModifiedBy\",\"IsUnique\":false,\"IsIdentity\":false},{\"$type\":\"Vanrise.GenericData.SQLDataStorage.SQLDataRecordStorageColumn, Vanrise.GenericData.SQLDataStorage\",\"ColumnName\":\"LastModifiedTime\",\"SQLDataType\":\"datetime\",\"ValueExpression\":\"LastModifiedTime\",\"IsUnique\":false,\"IsIdentity\":false}]},\"NullableFields\":{\"$type\":\"System.Collections.Generic.List`1[[Vanrise.GenericData.SQLDataStorage.NullableField, Vanrise.GenericData.SQLDataStorage]], mscorlib\",\"$values\":[]},\"IncludeQueueItemId\":false,\"GenerateRecordIds\":false,\"DateTimeField\":\"CreatedTime\",\"LastModifiedByField\":\"LastModifiedBy\",\"CreatedByField\":\"CreatedBy\",\"LastModifiedTimeField\":\"LastModifiedTime\",\"CreatedTimeField\":\"CreatedTime\",\"EnableUseCaching\":true,\"RequiredLimitResult\":false,\"DontReflectToDB\":false,\"DenyAPICall\":true,\"PermanentFilter\":{\"$type\":\"Vanrise.GenericData.Entities.DataRecordStoragePermanentFilter, Vanrise.GenericData.Entities\"},\"RequiredPermission\":{\"$type\":\"Vanrise.Security.Entities.RequiredPermissionSettings, Vanrise.Security.Entities\",\"Entries\":{\"$type\":\"System.Collections.Generic.List`1[[Vanrise.Security.Entities.RequiredPermissionEntry, Vanrise.Security.Entities]], mscorlib\",\"$values\":[]}},\"FieldsPermissions\":{\"$type\":\"System.Collections.Generic.List`1[[Vanrise.GenericData.Entities.DataRecordStorageFieldsPermission, Vanrise.GenericData.Entities]], mscorlib\",\"$values\":[]}}",
              "State": null,
              "CreatedTime": "2019-07-01T14:44:45.82",
              "LastModifiedTime": "2019-09-17T11:13:07.803"
            }
          }
        ],
        "Columns": [
          {
            "$type": "Vanrise.DevTools.Business.MergeGeneratedScriptItemColumn, Vanrise.DevTools.Business",
            "ColumnName": "ID",
            "IsIdentifier": true,
            "IncludeInInsert": true,
            "IncludeInUpdate": true
          },
          {
            "$type": "Vanrise.DevTools.Business.MergeGeneratedScriptItemColumn, Vanrise.DevTools.Business",
            "ColumnName": "Name",
            "IsIdentifier": false,
            "IncludeInInsert": true,
            "IncludeInUpdate": true
          },
          {
            "$type": "Vanrise.DevTools.Business.MergeGeneratedScriptItemColumn, Vanrise.DevTools.Business",
            "ColumnName": "DataRecordTypeID",
            "IsIdentifier": false,
            "IncludeInInsert": true,
            "IncludeInUpdate": true
          },
          {
            "$type": "Vanrise.DevTools.Business.MergeGeneratedScriptItemColumn, Vanrise.DevTools.Business",
            "ColumnName": "DataStoreID",
            "IsIdentifier": false,
            "IncludeInInsert": true,
            "IncludeInUpdate": true
          },
          {
            "$type": "Vanrise.DevTools.Business.MergeGeneratedScriptItemColumn, Vanrise.DevTools.Business",
            "ColumnName": "Settings",
            "IsIdentifier": false,
            "IncludeInInsert": true,
            "IncludeInUpdate": true
          },
          {
            "$type": "Vanrise.DevTools.Business.MergeGeneratedScriptItemColumn, Vanrise.DevTools.Business",
            "ColumnName": "State",
            "IsIdentifier": false,
            "IncludeInInsert": true,
            "IncludeInUpdate": true
          },
          {
            "$type": "Vanrise.DevTools.Business.MergeGeneratedScriptItemColumn, Vanrise.DevTools.Business",
            "ColumnName": "CreatedTime",
            "IsIdentifier": false,
            "IncludeInInsert": true,
            "IncludeInUpdate": true
          },
          {
            "$type": "Vanrise.DevTools.Business.MergeGeneratedScriptItemColumn, Vanrise.DevTools.Business",
            "ColumnName": "LastModifiedTime",
            "IsIdentifier": false,
            "IncludeInInsert": true,
            "IncludeInUpdate": true
          }
        ],
        "IsIdentity": false,
        "Variables": [],
        "LastWhereCondition": "rec.DevProjectID = 'c3cbcab4-fc87-4528-9323-decb35cec62d'",
        "LastJoinStatement": "JOIN genericdata.DataRecordType rec on MainTable.DataRecordTypeID = rec.ID",
        "ConfigId": "9837cad1-1f8f-4edf-8aab-25864c4ef842"
      },
      "Title": "Merge"
    },
    {
      "$type": "Vanrise.DevTools.Entities.GeneratedScriptItemTable, Vanrise.DevTools.Entities",
      "ConnectionId": "719772f8-053d-48f7-9760-3ac83132700f",
      "Schema": "genericdata",
      "TableName": "BusinessEntityDefinition",
      "Note": null,
      "Settings": {
        "$type": "Vanrise.DevTools.Business.MergeGeneratedScriptItem, Vanrise.DevTools.Business",
        "ConfigId": "9837cad1-1f8f-4edf-8aab-25864c4ef842",
        "Columns": [
          {
            "$type": "Vanrise.DevTools.Business.MergeGeneratedScriptItemColumn, Vanrise.DevTools.Business",
            "ColumnName": "ID",
            "IsIdentifier": true,
            "IncludeInInsert": true,
            "IncludeInUpdate": true
          },
          {
            "$type": "Vanrise.DevTools.Business.MergeGeneratedScriptItemColumn, Vanrise.DevTools.Business",
            "ColumnName": "DevProjectID",
            "IsIdentifier": false,
            "IncludeInInsert": true,
            "IncludeInUpdate": true
          },
          {
            "$type": "Vanrise.DevTools.Business.MergeGeneratedScriptItemColumn, Vanrise.DevTools.Business",
            "ColumnName": "Name",
            "IsIdentifier": false,
            "IncludeInInsert": true,
            "IncludeInUpdate": true
          },
          {
            "$type": "Vanrise.DevTools.Business.MergeGeneratedScriptItemColumn, Vanrise.DevTools.Business",
            "ColumnName": "Title",
            "IsIdentifier": false,
            "IncludeInInsert": true,
            "IncludeInUpdate": true
          },
          {
            "$type": "Vanrise.DevTools.Business.MergeGeneratedScriptItemColumn, Vanrise.DevTools.Business",
            "ColumnName": "Settings",
            "IsIdentifier": false,
            "IncludeInInsert": true,
            "IncludeInUpdate": true
          },
          {
            "$type": "Vanrise.DevTools.Business.MergeGeneratedScriptItemColumn, Vanrise.DevTools.Business",
            "ColumnName": "CreatedTime",
            "IsIdentifier": false,
            "IncludeInInsert": true,
            "IncludeInUpdate": true
          },
          {
            "$type": "Vanrise.DevTools.Business.MergeGeneratedScriptItemColumn, Vanrise.DevTools.Business",
            "ColumnName": "LastModifiedTime",
            "IsIdentifier": false,
            "IncludeInInsert": true,
            "IncludeInUpdate": true
          }
        ],
        "DataRows": [
          {
            "$type": "Vanrise.DevTools.Entities.GeneratedScriptItemTableRow, Vanrise.DevTools.Entities",
            "FieldValues": {
              "ID": "fe36264a-1db1-4c1d-9228-036a43195d4d",
              "DevProjectID": "c3cbcab4-fc87-4528-9323-decb35cec62d",
              "Name": "VRNumberPrefixType",
              "Title": "Number Prefix Type",
              "Settings": "{\"$type\":\"Vanrise.GenericData.Business.GenericBEDefinitionSettings, Vanrise.GenericData.Business\",\"ConfigId\":\"6f3fbd7b-275a-4d92-8e06-ad7f7b04c7d6\",\"IdType\":\"System.Guid\",\"DefinitionEditor\":\"vr-genericdata-genericbusinessentity-editor\",\"ViewerEditor\":\"vr-genericdata-genericbusinessentity-runtimeeditor\",\"SelectorFilterEditor\":\"vr-genericdata-genericbusinessentity-selectorfilter\",\"SelectorUIControl\":\"vr-genericdata-genericbusinessentity-selector\",\"ManagerFQTN\":\"Vanrise.GenericData.Business.GenericBusinessEntityManager, Vanrise.GenericData.Business\",\"WorkFlowAddBEActivityEditor\":\"businessprocess-vr-workflowactivity-addbusinessentity-settings\",\"WorkFlowUpdateBEActivityEditor\":\"businessprocess-vr-workflowactivity-updatebusinessentity-settings\",\"WorkFlowGetBEActivityEditor\":\"businessprocess-vr-workflowactivity-getbusinessentity-settings\",\"GenericBEType\":0,\"IsRemoteSelector\":false,\"HideAddButton\":false,\"DoNotLoadByDefault\":false,\"HideViewInfo\":false,\"EditorSize\":1,\"DataRecordTypeId\":\"79f76dca-ec83-4919-a09e-6f142578e7f7\",\"DataRecordStorageId\":\"36b1b656-a438-4e67-887b-5082126606d2\",\"TitleFieldName\":\"Name\",\"GenericBEActions\":{\"$type\":\"System.Collections.Generic.List`1[[Vanrise.GenericData.Business.GenericBEAction, Vanrise.GenericData.Business]], mscorlib\",\"$values\":[{\"$type\":\"Vanrise.GenericData.Business.GenericBEAction, Vanrise.GenericData.Business\",\"GenericBEActionId\":\"06fee618-a1d3-360f-f38f-b2e59de63cfc\",\"Name\":\"Edit\",\"Settings\":{\"$type\":\"Vanrise.GenericData.MainExtensions.EditGenericBEAction, Vanrise.GenericData.MainExtensions\",\"ConfigId\":\"293b2fab-6abe-4be7-ad58-7d9fa0ba9524\",\"ActionTypeName\":\"EditGenericBEAction\",\"ActionKind\":\"Edit\",\"OnlyView\":false}}]},\"GridDefinition\":{\"$type\":\"Vanrise.GenericData.Business.GenericBEGridDefinition, Vanrise.GenericData.Business\",\"ColumnDefinitions\":{\"$type\":\"System.Collections.Generic.List`1[[Vanrise.GenericData.Business.GenericBEGridColumn, Vanrise.GenericData.Business]], mscorlib\",\"$values\":[{\"$type\":\"Vanrise.GenericData.Business.GenericBEGridColumn, Vanrise.GenericData.Business\",\"FieldName\":\"Id\",\"FieldTitle\":\"Id\",\"GridColumnSettings\":{\"$type\":\"Vanrise.Entities.GridColumnSettings, Vanrise.Entities\",\"Width\":\"Normal\"}},{\"$type\":\"Vanrise.GenericData.Business.GenericBEGridColumn, Vanrise.GenericData.Business\",\"FieldName\":\"Name\",\"FieldTitle\":\"Name\",\"GridColumnSettings\":{\"$type\":\"Vanrise.Entities.GridColumnSettings, Vanrise.Entities\",\"Width\":\"Normal\"}}]},\"GenericBEGridActions\":{\"$type\":\"System.Collections.Generic.List`1[[Vanrise.GenericData.Business.GenericBEGridAction, Vanrise.GenericData.Business]], mscorlib\",\"$values\":[{\"$type\":\"Vanrise.GenericData.Business.GenericBEGridAction, Vanrise.GenericData.Business\",\"GenericBEGridActionId\":\"d063083a-7ccc-5f56-c65c-c2fe67f7c5c8\",\"GenericBEActionId\":\"06fee618-a1d3-360f-f38f-b2e59de63cfc\",\"Title\":\"Edit\",\"ReloadGridItem\":true}]},\"GenericBEGridActionGroups\":{\"$type\":\"System.Collections.Generic.List`1[[Vanrise.GenericData.Business.GenericBEGridActionGroup, Vanrise.GenericData.Business]], mscorlib\",\"$values\":[]},\"GenericBEGridViews\":{\"$type\":\"System.Collections.Generic.List`1[[Vanrise.GenericData.Business.GenericBEViewDefinition, Vanrise.GenericData.Business]], mscorlib\",\"$values\":[]}},\"EditorDefinition\":{\"$type\":\"Vanrise.GenericData.Business.GenericBEEditorDefinition, Vanrise.GenericData.Business\",\"Settings\":{\"$type\":\"Vanrise.GenericData.MainExtensions.GenericEditorDefinitionSetting, Vanrise.GenericData.MainExtensions\",\"ConfigId\":\"5be30b11-8ee3-47eb-8269-41bdafe077e1\",\"RuntimeEditor\":\"vr-genericdata-genericeditorsetting-runtime\",\"Rows\":{\"$type\":\"System.Collections.Generic.List`1[[Vanrise.GenericData.Entities.GenericEditorRow, Vanrise.GenericData.Entities]], mscorlib\",\"$values\":[{\"$type\":\"Vanrise.GenericData.Entities.GenericEditorRow, Vanrise.GenericData.Entities\",\"Fields\":{\"$type\":\"System.Collections.Generic.List`1[[Vanrise.GenericData.Entities.GenericEditorField, Vanrise.GenericData.Entities]], mscorlib\",\"$values\":[{\"$type\":\"Vanrise.GenericData.Entities.GenericEditorField, Vanrise.GenericData.Entities\",\"IsRequired\":true,\"IsDisabled\":false,\"ShowAsLabel\":false,\"HideLabel\":false,\"ReadOnly\":false,\"FieldPath\":\"Name\",\"FieldTitle\":\"Name\"}]}}]}}},\"FilterDefinition\":{\"$type\":\"Vanrise.GenericData.Business.GenericBEFilterDefinition, Vanrise.GenericData.Business\",\"Settings\":{\"$type\":\"Vanrise.GenericData.MainExtensions.GenericFilterDefinitionSettings, Vanrise.GenericData.MainExtensions\",\"ConfigId\":\"6d005236-ece6-43a1-b8ea-281bc0e7643e\",\"RuntimeEditor\":\"vr-genericdata-genericbe-filterruntime-generic\",\"FieldName\":\"Name\",\"FieldTitle\":\"Name\",\"IsRequired\":false,\"TriggerSearch\":false}},\"GenericBEBulkActions\":{\"$type\":\"System.Collections.Generic.List`1[[Vanrise.GenericData.Business.GenericBEBulkAction, Vanrise.GenericData.Business]], mscorlib\",\"$values\":[]},\"ShowUpload\":false,\"CanBeViewedFromRelatedGenericBE\":false,\"CustomActions\":{\"$type\":\"System.Collections.Generic.List`1[[Vanrise.GenericData.Business.GenericBECustomAction, Vanrise.GenericData.Business]], mscorlib\",\"$values\":[]},\"ThreeSixtyDegreeSettings\":{\"$type\":\"Vanrise.GenericData.Business.GenericBE360DegreeSettings, Vanrise.GenericData.Business\",\"Use360Degree\":false,\"DirectiveSettings\":{\"$type\":\"Vanrise.GenericData.Business.GenericBE360DegreeViewSettings, Vanrise.GenericData.Business\"}},\"Security\":{\"$type\":\"Vanrise.GenericData.Business.GenericBEDefinitionSecurity, Vanrise.GenericData.Business\",\"ViewRequiredPermission\":{\"$type\":\"Vanrise.Security.Entities.RequiredPermissionSettings, Vanrise.Security.Entities\",\"Entries\":{\"$type\":\"System.Collections.Generic.List`1[[Vanrise.Security.Entities.RequiredPermissionEntry, Vanrise.Security.Entities]], mscorlib\",\"$values\":[{\"$type\":\"Vanrise.Security.Entities.RequiredPermissionEntry, Vanrise.Security.Entities\",\"EntityId\":\"a99a836d-0c03-4946-a0e2-5a758354807b\",\"PermissionOptions\":{\"$type\":\"System.Collections.Generic.List`1[[System.String, mscorlib]], mscorlib\",\"$values\":[\"View\"]}}]}},\"AddRequiredPermission\":{\"$type\":\"Vanrise.Security.Entities.RequiredPermissionSettings, Vanrise.Security.Entities\",\"Entries\":{\"$type\":\"System.Collections.Generic.List`1[[Vanrise.Security.Entities.RequiredPermissionEntry, Vanrise.Security.Entities]], mscorlib\",\"$values\":[{\"$type\":\"Vanrise.Security.Entities.RequiredPermissionEntry, Vanrise.Security.Entities\",\"EntityId\":\"a99a836d-0c03-4946-a0e2-5a758354807b\",\"PermissionOptions\":{\"$type\":\"System.Collections.Generic.List`1[[System.String, mscorlib]], mscorlib\",\"$values\":[\"Manage\"]}}]}},\"EditRequiredPermission\":{\"$type\":\"Vanrise.Security.Entities.RequiredPermissionSettings, Vanrise.Security.Entities\",\"Entries\":{\"$type\":\"System.Collections.Generic.List`1[[Vanrise.Security.Entities.RequiredPermissionEntry, Vanrise.Security.Entities]], mscorlib\",\"$values\":[{\"$type\":\"Vanrise.Security.Entities.RequiredPermissionEntry, Vanrise.Security.Entities\",\"EntityId\":\"a99a836d-0c03-4946-a0e2-5a758354807b\",\"PermissionOptions\":{\"$type\":\"System.Collections.Generic.List`1[[System.String, mscorlib]], mscorlib\",\"$values\":[\"Manage\"]}}]}}}}",
              "CreatedTime": "2019-07-01T14:44:45.82",
              "LastModifiedTime": "2019-10-16T14:25:33.88"
            }
          },
          {
            "$type": "Vanrise.DevTools.Entities.GeneratedScriptItemTableRow, Vanrise.DevTools.Entities",
            "FieldValues": {
              "ID": "992c93a5-0d90-41cd-8501-7235b4cab09e",
              "DevProjectID": "c3cbcab4-fc87-4528-9323-decb35cec62d",
              "Name": "VRNumberPrefix",
              "Title": "Number Prefix",
              "Settings": "{\"$type\":\"Vanrise.GenericData.Business.GenericBEDefinitionSettings, Vanrise.GenericData.Business\",\"ConfigId\":\"6f3fbd7b-275a-4d92-8e06-ad7f7b04c7d6\",\"IdType\":\"System.Int32\",\"DefinitionEditor\":\"vr-genericdata-genericbusinessentity-editor\",\"ViewerEditor\":\"vr-genericdata-genericbusinessentity-runtimeeditor\",\"SelectorFilterEditor\":\"vr-genericdata-genericbusinessentity-selectorfilter\",\"SelectorUIControl\":\"vr-genericdata-genericbusinessentity-selector\",\"ManagerFQTN\":\"Vanrise.GenericData.Business.GenericBusinessEntityManager, Vanrise.GenericData.Business\",\"WorkFlowAddBEActivityEditor\":\"businessprocess-vr-workflowactivity-addbusinessentity-settings\",\"WorkFlowUpdateBEActivityEditor\":\"businessprocess-vr-workflowactivity-updatebusinessentity-settings\",\"WorkFlowGetBEActivityEditor\":\"businessprocess-vr-workflowactivity-getbusinessentity-settings\",\"GenericBEType\":0,\"IsRemoteSelector\":false,\"HideAddButton\":false,\"DoNotLoadByDefault\":false,\"HideViewInfo\":false,\"EditorSize\":1,\"DataRecordTypeId\":\"630e82e3-e187-4738-a40d-387f07cb4759\",\"DataRecordStorageId\":\"a70a6875-0820-42c2-9ec0-0591ba6f2778\",\"TitleFieldName\":\"Number\",\"GenericBEActions\":{\"$type\":\"System.Collections.Generic.List`1[[Vanrise.GenericData.Business.GenericBEAction, Vanrise.GenericData.Business]], mscorlib\",\"$values\":[{\"$type\":\"Vanrise.GenericData.Business.GenericBEAction, Vanrise.GenericData.Business\",\"GenericBEActionId\":\"3f6db5ce-0b5d-5189-d5b0-ca3750a2eb34\",\"Name\":\"Edit\",\"Settings\":{\"$type\":\"Vanrise.GenericData.MainExtensions.EditGenericBEAction, Vanrise.GenericData.MainExtensions\",\"ConfigId\":\"293b2fab-6abe-4be7-ad58-7d9fa0ba9524\",\"ActionTypeName\":\"EditGenericBEAction\",\"ActionKind\":\"Edit\",\"OnlyView\":false}}]},\"GridDefinition\":{\"$type\":\"Vanrise.GenericData.Business.GenericBEGridDefinition, Vanrise.GenericData.Business\",\"ColumnDefinitions\":{\"$type\":\"System.Collections.Generic.List`1[[Vanrise.GenericData.Business.GenericBEGridColumn, Vanrise.GenericData.Business]], mscorlib\",\"$values\":[{\"$type\":\"Vanrise.GenericData.Business.GenericBEGridColumn, Vanrise.GenericData.Business\",\"FieldName\":\"Number\",\"FieldTitle\":\"Number\",\"GridColumnSettings\":{\"$type\":\"Vanrise.Entities.GridColumnSettings, Vanrise.Entities\",\"Width\":\"Normal\"}},{\"$type\":\"Vanrise.GenericData.Business.GenericBEGridColumn, Vanrise.GenericData.Business\",\"FieldName\":\"Type\",\"FieldTitle\":\"Type\",\"GridColumnSettings\":{\"$type\":\"Vanrise.Entities.GridColumnSettings, Vanrise.Entities\",\"Width\":\"Normal\"}},{\"$type\":\"Vanrise.GenericData.Business.GenericBEGridColumn, Vanrise.GenericData.Business\",\"FieldName\":\"IsExact\",\"FieldTitle\":\"Exact\",\"GridColumnSettings\":{\"$type\":\"Vanrise.Entities.GridColumnSettings, Vanrise.Entities\",\"Width\":\"Normal\"}}]},\"GenericBEGridActions\":{\"$type\":\"System.Collections.Generic.List`1[[Vanrise.GenericData.Business.GenericBEGridAction, Vanrise.GenericData.Business]], mscorlib\",\"$values\":[{\"$type\":\"Vanrise.GenericData.Business.GenericBEGridAction, Vanrise.GenericData.Business\",\"GenericBEGridActionId\":\"85206f83-249d-4cf8-eece-60d3d7fed461\",\"GenericBEActionId\":\"3f6db5ce-0b5d-5189-d5b0-ca3750a2eb34\",\"Title\":\"Edit\",\"ReloadGridItem\":true}]},\"GenericBEGridActionGroups\":{\"$type\":\"System.Collections.Generic.List`1[[Vanrise.GenericData.Business.GenericBEGridActionGroup, Vanrise.GenericData.Business]], mscorlib\",\"$values\":[]},\"GenericBEGridViews\":{\"$type\":\"System.Collections.Generic.List`1[[Vanrise.GenericData.Business.GenericBEViewDefinition, Vanrise.GenericData.Business]], mscorlib\",\"$values\":[]}},\"EditorDefinition\":{\"$type\":\"Vanrise.GenericData.Business.GenericBEEditorDefinition, Vanrise.GenericData.Business\",\"Settings\":{\"$type\":\"Vanrise.GenericData.MainExtensions.GenericEditorDefinitionSetting, Vanrise.GenericData.MainExtensions\",\"ConfigId\":\"5be30b11-8ee3-47eb-8269-41bdafe077e1\",\"RuntimeEditor\":\"vr-genericdata-genericeditorsetting-runtime\",\"Rows\":{\"$type\":\"System.Collections.Generic.List`1[[Vanrise.GenericData.Entities.GenericEditorRow, Vanrise.GenericData.Entities]], mscorlib\",\"$values\":[{\"$type\":\"Vanrise.GenericData.Entities.GenericEditorRow, Vanrise.GenericData.Entities\",\"Fields\":{\"$type\":\"System.Collections.Generic.List`1[[Vanrise.GenericData.Entities.GenericEditorField, Vanrise.GenericData.Entities]], mscorlib\",\"$values\":[{\"$type\":\"Vanrise.GenericData.Entities.GenericEditorField, Vanrise.GenericData.Entities\",\"IsRequired\":true,\"IsDisabled\":false,\"ShowAsLabel\":false,\"HideLabel\":false,\"ReadOnly\":false,\"FieldPath\":\"Number\",\"FieldTitle\":\"Number\"},{\"$type\":\"Vanrise.GenericData.Entities.GenericEditorField, Vanrise.GenericData.Entities\",\"IsRequired\":true,\"IsDisabled\":false,\"ShowAsLabel\":false,\"HideLabel\":false,\"ReadOnly\":false,\"FieldPath\":\"Type\",\"FieldTitle\":\"Type\"},{\"$type\":\"Vanrise.GenericData.Entities.GenericEditorField, Vanrise.GenericData.Entities\",\"IsRequired\":false,\"IsDisabled\":false,\"ShowAsLabel\":false,\"HideLabel\":false,\"ReadOnly\":false,\"FieldPath\":\"IsExact\",\"FieldTitle\":\"Exact\"}]}}]}}},\"FilterDefinition\":{\"$type\":\"Vanrise.GenericData.Business.GenericBEFilterDefinition, Vanrise.GenericData.Business\",\"Settings\":{\"$type\":\"Vanrise.GenericData.MainExtensions.BasicAdvancedFilterDefinitionSettings, Vanrise.GenericData.MainExtensions\",\"ConfigId\":\"8082ffc6-6781-4501-aa31-02493d74cb8f\",\"RuntimeEditor\":\"vr-genericdata-genericbe-filterruntime-basicadvanced\",\"Filters\":{\"$type\":\"System.Collections.Generic.List`1[[Vanrise.GenericData.MainExtensions.BasicAdvancedFilterItem, Vanrise.GenericData.MainExtensions]], mscorlib\",\"$values\":[{\"$type\":\"Vanrise.GenericData.MainExtensions.BasicAdvancedFilterItem, Vanrise.GenericData.MainExtensions\",\"BasicAdvancedFilterItemId\":\"8adcc5a1-a4c0-4eb0-37a8-7bc922fdd768\",\"Name\":\"Number\",\"ShowInBasic\":false,\"FilterSettings\":{\"$type\":\"Vanrise.GenericData.MainExtensions.GenericFilterDefinitionSettings, Vanrise.GenericData.MainExtensions\",\"ConfigId\":\"6d005236-ece6-43a1-b8ea-281bc0e7643e\",\"RuntimeEditor\":\"vr-genericdata-genericbe-filterruntime-generic\",\"FieldName\":\"Number\",\"FieldTitle\":\"Number\",\"IsRequired\":false,\"TriggerSearch\":false}},{\"$type\":\"Vanrise.GenericData.MainExtensions.BasicAdvancedFilterItem, Vanrise.GenericData.MainExtensions\",\"BasicAdvancedFilterItemId\":\"dd6176e5-0c7b-cbce-aaff-1a72dfbb26d7\",\"Name\":\"Type\",\"ShowInBasic\":false,\"FilterSettings\":{\"$type\":\"Vanrise.GenericData.MainExtensions.GenericFilterDefinitionSettings, Vanrise.GenericData.MainExtensions\",\"ConfigId\":\"6d005236-ece6-43a1-b8ea-281bc0e7643e\",\"RuntimeEditor\":\"vr-genericdata-genericbe-filterruntime-generic\",\"FieldName\":\"Type\",\"FieldTitle\":\"Type\",\"IsRequired\":false,\"TriggerSearch\":false}},{\"$type\":\"Vanrise.GenericData.MainExtensions.BasicAdvancedFilterItem, Vanrise.GenericData.MainExtensions\",\"BasicAdvancedFilterItemId\":\"af4c5b9e-216b-7481-150c-8f8abc7af5b0\",\"Name\":\"Exact\",\"ShowInBasic\":false,\"FilterSettings\":{\"$type\":\"Vanrise.GenericData.MainExtensions.GenericFilterDefinitionSettings, Vanrise.GenericData.MainExtensions\",\"ConfigId\":\"6d005236-ece6-43a1-b8ea-281bc0e7643e\",\"RuntimeEditor\":\"vr-genericdata-genericbe-filterruntime-generic\",\"FieldName\":\"IsExact\",\"FieldTitle\":\"Exact\",\"IsRequired\":false,\"TriggerSearch\":false}}]}}},\"GenericBEBulkActions\":{\"$type\":\"System.Collections.Generic.List`1[[Vanrise.GenericData.Business.GenericBEBulkAction, Vanrise.GenericData.Business]], mscorlib\",\"$values\":[]},\"ShowUpload\":false,\"CanBeViewedFromRelatedGenericBE\":false,\"CustomActions\":{\"$type\":\"System.Collections.Generic.List`1[[Vanrise.GenericData.Business.GenericBECustomAction, Vanrise.GenericData.Business]], mscorlib\",\"$values\":[]},\"ThreeSixtyDegreeSettings\":{\"$type\":\"Vanrise.GenericData.Business.GenericBE360DegreeSettings, Vanrise.GenericData.Business\",\"Use360Degree\":false,\"DirectiveSettings\":{\"$type\":\"Vanrise.GenericData.Business.GenericBE360DegreeViewSettings, Vanrise.GenericData.Business\"}},\"Security\":{\"$type\":\"Vanrise.GenericData.Business.GenericBEDefinitionSecurity, Vanrise.GenericData.Business\",\"ViewRequiredPermission\":{\"$type\":\"Vanrise.Security.Entities.RequiredPermissionSettings, Vanrise.Security.Entities\",\"Entries\":{\"$type\":\"System.Collections.Generic.List`1[[Vanrise.Security.Entities.RequiredPermissionEntry, Vanrise.Security.Entities]], mscorlib\",\"$values\":[{\"$type\":\"Vanrise.Security.Entities.RequiredPermissionEntry, Vanrise.Security.Entities\",\"EntityId\":\"a99a836d-0c03-4946-a0e2-5a758354807b\",\"PermissionOptions\":{\"$type\":\"System.Collections.Generic.List`1[[System.String, mscorlib]], mscorlib\",\"$values\":[\"View\"]}}]}},\"AddRequiredPermission\":{\"$type\":\"Vanrise.Security.Entities.RequiredPermissionSettings, Vanrise.Security.Entities\",\"Entries\":{\"$type\":\"System.Collections.Generic.List`1[[Vanrise.Security.Entities.RequiredPermissionEntry, Vanrise.Security.Entities]], mscorlib\",\"$values\":[{\"$type\":\"Vanrise.Security.Entities.RequiredPermissionEntry, Vanrise.Security.Entities\",\"EntityId\":\"a99a836d-0c03-4946-a0e2-5a758354807b\",\"PermissionOptions\":{\"$type\":\"System.Collections.Generic.List`1[[System.String, mscorlib]], mscorlib\",\"$values\":[\"Manage\"]}}]}},\"EditRequiredPermission\":{\"$type\":\"Vanrise.Security.Entities.RequiredPermissionSettings, Vanrise.Security.Entities\",\"Entries\":{\"$type\":\"System.Collections.Generic.List`1[[Vanrise.Security.Entities.RequiredPermissionEntry, Vanrise.Security.Entities]], mscorlib\",\"$values\":[{\"$type\":\"Vanrise.Security.Entities.RequiredPermissionEntry, Vanrise.Security.Entities\",\"EntityId\":\"a99a836d-0c03-4946-a0e2-5a758354807b\",\"PermissionOptions\":{\"$type\":\"System.Collections.Generic.List`1[[System.String, mscorlib]], mscorlib\",\"$values\":[\"Manage\"]}}]}}}}",
              "CreatedTime": "2019-07-01T14:44:45.82",
              "LastModifiedTime": "2019-09-27T11:53:35.583"
            }
          }
        ],
        "Variables": null,
        "LastWhereCondition": "DevProjectID = 'c3cbcab4-fc87-4528-9323-decb35cec62d'",
        "LastJoinStatement": null,
        "IsIdentity": false
      },
      "Title": "Merge"
    },
    {
      "ConnectionId": "719772f8-053d-48f7-9760-3ac83132700f",
      "Schema": "sec",
      "TableName": "View",
      "Note": null,
      "Settings": {
        "$type": "Vanrise.DevTools.Business.MergeGeneratedScriptItem, Vanrise.DevTools.Business",
        "DataRows": [
          {
            "FieldValues": {
              "ID": "fd633feb-5073-449d-84c9-2b7eddcac43d",
              "DevProjectID": "c3cbcab4-fc87-4528-9323-decb35cec62d",
              "Name": "Number Prefix Type",
              "Title": "Number Prefix Type",
              "Url": null,
              "Module": "89254e36-5d91-4db1-970f-9bfef404679a",
              "ActionNames": null,
              "Audience": null,
              "Content": null,
              "Settings": "{\"$type\":\"Vanrise.GenericData.Business.GenericBEViewSettings, Vanrise.GenericData.Business\",\"Settings\":{\"$type\":\"System.Collections.Generic.List`1[[Vanrise.GenericData.Business.GenericBEViewSettingItem, Vanrise.GenericData.Business]], mscorlib\",\"$values\":[{\"$type\":\"Vanrise.GenericData.Business.GenericBEViewSettingItem, Vanrise.GenericData.Business\",\"BusinessEntityDefinitionId\":\"fe36264a-1db1-4c1d-9228-036a43195d4d\"}]}}",
              "Type": "b99b2b0a-9a80-49fc-b68f-c946e1628595",
              "Rank": 50,
              "CreatedTime": "2019-07-01T14:44:45.82",
              "LastModifiedTime": "2019-10-15T11:18:46.32"
            }
          },
          {
            "FieldValues": {
              "ID": "09f03a5b-eec4-4418-8a63-771b66e640a9",
              "DevProjectID": "c3cbcab4-fc87-4528-9323-decb35cec62d",
              "Name": "Number Prefix",
              "Title": "Number Prefix",
              "Url": null,
              "Module": "89254e36-5d91-4db1-970f-9bfef404679a",
              "ActionNames": null,
              "Audience": null,
              "Content": null,
              "Settings": "{\"$type\":\"Vanrise.GenericData.Business.GenericBEViewSettings, Vanrise.GenericData.Business\",\"Settings\":{\"$type\":\"System.Collections.Generic.List`1[[Vanrise.GenericData.Business.GenericBEViewSettingItem, Vanrise.GenericData.Business]], mscorlib\",\"$values\":[{\"$type\":\"Vanrise.GenericData.Business.GenericBEViewSettingItem, Vanrise.GenericData.Business\",\"BusinessEntityDefinitionId\":\"992c93a5-0d90-41cd-8501-7235b4cab09e\"}]}}",
              "Type": "b99b2b0a-9a80-49fc-b68f-c946e1628595",
              "Rank": 51,
              "CreatedTime": "2019-07-01T14:44:45.82",
              "LastModifiedTime": "2019-10-15T11:18:46.32"
            }
          }
        ],
        "Columns": [
          {
            "$type": "Vanrise.DevTools.Business.MergeGeneratedScriptItemColumn, Vanrise.DevTools.Business",
            "ColumnName": "ID",
            "IsIdentifier": true,
            "IncludeInInsert": true,
            "IncludeInUpdate": true
          },
          {
            "$type": "Vanrise.DevTools.Business.MergeGeneratedScriptItemColumn, Vanrise.DevTools.Business",
            "ColumnName": "DevProjectID",
            "IsIdentifier": false,
            "IncludeInInsert": true,
            "IncludeInUpdate": true
          },
          {
            "$type": "Vanrise.DevTools.Business.MergeGeneratedScriptItemColumn, Vanrise.DevTools.Business",
            "ColumnName": "Name",
            "IsIdentifier": false,
            "IncludeInInsert": true,
            "IncludeInUpdate": true
          },
          {
            "$type": "Vanrise.DevTools.Business.MergeGeneratedScriptItemColumn, Vanrise.DevTools.Business",
            "ColumnName": "Title",
            "IsIdentifier": false,
            "IncludeInInsert": true,
            "IncludeInUpdate": true
          },
          {
            "$type": "Vanrise.DevTools.Business.MergeGeneratedScriptItemColumn, Vanrise.DevTools.Business",
            "ColumnName": "Url",
            "IsIdentifier": false,
            "IncludeInInsert": true,
            "IncludeInUpdate": true
          },
          {
            "$type": "Vanrise.DevTools.Business.MergeGeneratedScriptItemColumn, Vanrise.DevTools.Business",
            "ColumnName": "Module",
            "IsIdentifier": false,
            "IncludeInInsert": true,
            "IncludeInUpdate": true
          },
          {
            "$type": "Vanrise.DevTools.Business.MergeGeneratedScriptItemColumn, Vanrise.DevTools.Business",
            "ColumnName": "ActionNames",
            "IsIdentifier": false,
            "IncludeInInsert": true,
            "IncludeInUpdate": true
          },
          {
            "$type": "Vanrise.DevTools.Business.MergeGeneratedScriptItemColumn, Vanrise.DevTools.Business",
            "ColumnName": "Audience",
            "IsIdentifier": false,
            "IncludeInInsert": true,
            "IncludeInUpdate": true
          },
          {
            "$type": "Vanrise.DevTools.Business.MergeGeneratedScriptItemColumn, Vanrise.DevTools.Business",
            "ColumnName": "Content",
            "IsIdentifier": false,
            "IncludeInInsert": true,
            "IncludeInUpdate": true
          },
          {
            "$type": "Vanrise.DevTools.Business.MergeGeneratedScriptItemColumn, Vanrise.DevTools.Business",
            "ColumnName": "Settings",
            "IsIdentifier": false,
            "IncludeInInsert": true,
            "IncludeInUpdate": true
          },
          {
            "$type": "Vanrise.DevTools.Business.MergeGeneratedScriptItemColumn, Vanrise.DevTools.Business",
            "ColumnName": "Type",
            "IsIdentifier": false,
            "IncludeInInsert": true,
            "IncludeInUpdate": true
          },
          {
            "$type": "Vanrise.DevTools.Business.MergeGeneratedScriptItemColumn, Vanrise.DevTools.Business",
            "ColumnName": "Rank",
            "IsIdentifier": false,
            "IncludeInInsert": true,
            "IncludeInUpdate": true
          },
          {
            "$type": "Vanrise.DevTools.Business.MergeGeneratedScriptItemColumn, Vanrise.DevTools.Business",
            "ColumnName": "CreatedTime",
            "IsIdentifier": false,
            "IncludeInInsert": true,
            "IncludeInUpdate": true
          },
          {
            "$type": "Vanrise.DevTools.Business.MergeGeneratedScriptItemColumn, Vanrise.DevTools.Business",
            "ColumnName": "LastModifiedTime",
            "IsIdentifier": false,
            "IncludeInInsert": true,
            "IncludeInUpdate": true
          }
        ],
        "IsIdentity": false,
        "Variables": [],
        "LastWhereCondition": "DevProjectID = 'c3cbcab4-fc87-4528-9323-decb35cec62d'",
        "LastJoinStatement": null,
        "ConfigId": "9837cad1-1f8f-4edf-8aab-25864c4ef842"
      },
      "Title": "Merge"
    }
  ]
}